agent_patterns/__init__.py
agent_patterns/core/__init__.py
agent_patterns/core/base_agent.py
agent_patterns/core/prompts.py
agent_patterns/core/memory/__init__.py
agent_patterns/core/memory/base.py
agent_patterns/core/memory/composite.py
agent_patterns/core/memory/episodic.py
agent_patterns/core/memory/procedural.py
agent_patterns/core/memory/provider.py
agent_patterns/core/memory/semantic.py
agent_patterns/core/memory/persistence/__init__.py
agent_patterns/core/memory/persistence/file_system.py
agent_patterns/core/memory/persistence/in_memory.py
agent_patterns/core/memory/persistence/vector_store.py
agent_patterns/core/tools/__init__.py
agent_patterns/core/tools/base.py
agent_patterns/core/tools/provider.py
agent_patterns/core/tools/registry.py
agent_patterns/core/tools/providers/__init__.py
agent_patterns/core/tools/providers/mcp_provider.py
agent_patterns/patterns/__init__.py
agent_patterns/patterns/factory.py
agent_patterns/patterns/lats_agent.py
agent_patterns/patterns/llm_compiler_agent.py
agent_patterns/patterns/plan_and_solve_agent.py
agent_patterns/patterns/re_act_agent.py
agent_patterns/patterns/reflection_agent.py
agent_patterns/patterns/reflection_and_refinement_agent.py
agent_patterns/patterns/reflexion_agent.py
agent_patterns/patterns/rewoo_agent.py
agent_patterns/patterns/self_discovery_agent.py
agent_patterns/patterns/storm_agent.py
agent_patterns-0.1.4.dist-info/licenses/LICENSE
agent_patterns-0.1.4.dist-info/METADATA
agent_patterns-0.1.4.dist-info/WHEEL
agent_patterns-0.1.4.dist-info/top_level.txt
agent_patterns-0.1.4.dist-info/RECORD
