Metadata-Version: 2.4
Name: agent-patterns
Version: 0.1.4
Summary: A library of reusable, extensible AI agent patterns using LangGraph
Author-email: Michael Caughey <mcaughey001@caughey.com>
License: MIT
Project-URL: Homepage, https://github.com/osok/agent-patterns
Project-URL: Documentation, https://agent-patterns.readthedocs.io/
Project-URL: Bug Tracker, https://github.com/osok/agent-patterns/issues
Keywords: agent,ai,langgraph,langchain,patterns
Classifier: Development Status :: 3 - Alpha
Classifier: Intended Audience :: Developers
Classifier: License :: OSI Approved :: MIT License
Classifier: Programming Language :: Python :: 3
Classifier: Programming Language :: Python :: 3.8
Classifier: Programming Language :: Python :: 3.9
Classifier: Programming Language :: Python :: 3.10
Classifier: Programming Language :: Python :: 3.11
Requires-Python: >=3.8
License-File: LICENSE
Requires-Dist: langchain>=0.1.0
Requires-Dist: langgraph>=0.0.10
Requires-Dist: langchain-openai>=0.0.2
Requires-Dist: langchain-anthropic>=0.0.1
Requires-Dist: langchain-community>=0.0.13
Requires-Dist: python-dotenv>=1.0.0
Requires-Dist: openai>=1.12.0
Requires-Dist: anthropic>=0.8.0
Provides-Extra: dev
Requires-Dist: black>=24.0.0; extra == "dev"
Requires-Dist: isort>=5.13.0; extra == "dev"
Requires-Dist: mypy>=1.8.0; extra == "dev"
Requires-Dist: ruff>=0.2.0; extra == "dev"
Requires-Dist: pytest>=8.3.0; extra == "dev"
Requires-Dist: pytest-asyncio>=0.23.0; extra == "dev"
Requires-Dist: pytest-cov>=4.1.0; extra == "dev"
Provides-Extra: docs
Requires-Dist: mkdocs>=1.5.0; extra == "docs"
Requires-Dist: mkdocs-material>=9.0.0; extra == "docs"
Requires-Dist: mkdocstrings>=0.24.0; extra == "docs"
Requires-Dist: mkdocstrings-python>=1.7.0; extra == "docs"
Dynamic: license-file
